drumpler_mammoth/__init__.py
drumpler_mammoth/http_request.py
drumpler_mammoth/mammoth.py
drumpler_mammoth/mylogger.py
drumpler_mammoth-2.1.2.dist-info/LICENSE
drumpler_mammoth-2.1.2.dist-info/METADATA
drumpler_mammoth-2.1.2.dist-info/WHEEL
drumpler_mammoth-2.1.2.dist-info/top_level.txt
drumpler_mammoth-2.1.2.dist-info/RECORD
