Metadata-Version: 2.1
Name: drumpler_mammoth
Version: 2.1.2
Summary: Framework for rapidly developing a restful API that requires post processing
Home-page: https://github.com/KarelOmab/Drumpler-Mammoth
Author: Karel Tutsu
Author-email: karel.tutsu@gmail.com
Classifier: Programming Language :: Python :: 3
Classifier: License :: OSI Approved :: MIT License
Classifier: Operating System :: OS Independent
Requires-Python: >=3.6
License-File: LICENSE
Requires-Dist: requests
Requires-Dist: python-dotenv
